yaologit/__init__.py
yaologit/config.py
yaologit/core.py
yaologit/exceptions.py
yaologit/utils.py
yaologit-0.2.0.dist-info/licenses/LICENSE
yaologit-0.2.0.dist-info/METADATA
yaologit-0.2.0.dist-info/WHEEL
yaologit-0.2.0.dist-info/top_level.txt
yaologit-0.2.0.dist-info/RECORD
