Metadata-Version: 2.4
Name: yaologit
Version: 0.2.0
Summary: A process-safe logging package based on loguru
Author-email: Yaohua Guo <guo.yaohua@foxmail.com>
Maintainer-email: Yaohua Guo <guo.yaohua@foxmail.com>
License-Expression: MIT
Project-URL: Homepage, https://github.com/guoyaohua/YaoLogit
Project-URL: Documentation, https://github.com/guoyaohua/YaoLogit#readme
Project-URL: Repository, https://github.com/guoyaohua/YaoLogit
Project-URL: Issues, https://github.com/guoyaohua/YaoLogit/issues
Keywords: logging,loguru,process-safe,multiprocessing,logger
Classifier: Development Status :: 4 - Beta
Classifier: Intended Audience :: Developers
Classifier: Topic :: Software Development :: Libraries :: Python Modules
Classifier: Topic :: System :: Logging
Classifier: Programming Language :: Python :: 3
Classifier: Programming Language :: Python :: 3.7
Classifier: Programming Language :: Python :: 3.8
Classifier: Programming Language :: Python :: 3.9
Classifier: Programming Language :: Python :: 3.10
Classifier: Programming Language :: Python :: 3.11
Classifier: Programming Language :: Python :: 3.12
Classifier: Operating System :: OS Independent
Requires-Python: >=3.7
License-File: LICENSE
Requires-Dist: loguru>=0.7.0
Requires-Dist: filelock>=3.0.0
Requires-Dist: importlib-metadata; python_version < "3.8"
Provides-Extra: dev
Requires-Dist: pytest>=7.0.0; extra == "dev"
Requires-Dist: pytest-cov>=4.0.0; extra == "dev"
Requires-Dist: black>=22.0.0; extra == "dev"
Requires-Dist: flake8>=5.0.0; extra == "dev"
Requires-Dist: mypy>=0.990; extra == "dev"
Requires-Dist: sphinx>=5.0.0; extra == "dev"
Requires-Dist: sphinx-rtd-theme>=1.0.0; extra == "dev"
Dynamic: license-file
